front11_div/__init__.py
front11_div/front11_div.py
Front11_div-0.6.0.dist-info/METADATA
Front11_div-0.6.0.dist-info/WHEEL
Front11_div-0.6.0.dist-info/top_level.txt
Front11_div-0.6.0.dist-info/RECORD
