Metadata-Version: 2.1
Name: Front11_div
Version: 0.6.0
Summary: Default template for PDM package
Author-email: Nicou11 <lyoungin1204@gmail.com>
License: MIT
Requires-Python: >=3.9
